setup.py
statcounter/__init__.py
statcounter/client.py
statcounter/conf.py
statcounter/url_builder.py
statcounter.egg-info/PKG-INFO
statcounter.egg-info/SOURCES.txt
statcounter.egg-info/dependency_links.txt
statcounter.egg-info/requires.txt
statcounter.egg-info/top_level.txt
statcounter/clients/__init__.py
statcounter/clients/account.py
statcounter/clients/base.py
statcounter/clients/projects.py
statcounter/clients/stats.py
statcounter/clients/tests/__init__.py
statcounter/clients/tests/test_stats_client.py
statcounter/tests/__init__.py
statcounter/tests/test_url_builder.py
statcounter/utils/__init__.py
statcounter/utils/date_range.py
statcounter/utils/tests/__init__.py
statcounter/utils/tests/test_date_range.py