Metadata-Version: 1.0
Name: statcounter
Version: 0.1
Summary: Statcounter API client
Home-page: https://github.com/v-hunt/Statcounter
Author: hunting
Author-email: VicHunting@yandex.ua
License: BSD
Platform: UNKNOWN
